obskit/__init__.py
obskit/_version.py
obskit/adaptive_sampling.py
obskit/alert_dedup.py
obskit/annotations.py
obskit/audit.py
obskit/autoscaling.py
obskit/batch.py
obskit/breakdown.py
obskit/budgets.py
obskit/business.py
obskit/cache.py
obskit/capacity.py
obskit/chaos.py
obskit/circuit_dashboard.py
obskit/compliance_reporter.py
obskit/config.py
obskit/config_file.py
obskit/consumer_lag.py
obskit/correlation.py
obskit/cost.py
obskit/degradation.py
obskit/dependency_graph.py
obskit/deployment.py
obskit/dlq.py
obskit/executor.py
obskit/external.py
obskit/failover.py
obskit/feature_flags.py
obskit/fingerprint.py
obskit/flamegraph.py
obskit/hot_path.py
obskit/incident_timeline.py
obskit/locking.py
obskit/memory.py
obskit/mixin.py
obskit/pools.py
obskit/py.typed
obskit/query_analyzer.py
obskit/quota.py
obskit/resource_predictor.py
obskit/root_cause.py
obskit/runbook.py
obskit/secrets_detector.py
obskit/self_healing.py
obskit/shedding.py
obskit/shutdown.py
obskit/sla_predictor.py
obskit/validation.py
obskit/alerts/__init__.py
obskit/alerts/config.py
obskit/alerts/rules_generator.py
obskit/alerts/slow_operation.py
obskit/compliance/pii.py
obskit/core/__init__.py
obskit/core/batch_context.py
obskit/core/context.py
obskit/core/deprecation.py
obskit/core/errors.py
obskit/core/types.py
obskit/dashboards/__init__.py
obskit/dashboards/grafana.py
obskit/db/__init__.py
obskit/db/sqlalchemy.py
obskit/db/tracker.py
obskit/debug/__init__.py
obskit/debug/replay.py
obskit/decorators/__init__.py
obskit/decorators/combined.py
obskit/errors/__init__.py
obskit/errors/responses.py
obskit/health/__init__.py
obskit/health/aggregator.py
obskit/health/checker.py
obskit/health/checks.py
obskit/health/server.py
obskit/health/slo_check.py
obskit/interfaces/__init__.py
obskit/interfaces/circuit_breaker.py
obskit/interfaces/health_checker.py
obskit/interfaces/logging.py
obskit/interfaces/metrics.py
obskit/interfaces/tracer.py
obskit/logging/__init__.py
obskit/logging/dynamic.py
obskit-1.5.0.dist-info/METADATA
obskit-1.5.0.dist-info/WHEEL
obskit-1.5.0.dist-info/licenses/LICENSE
obskit-1.5.0.dist-info/RECORD
