Metadata-Version: 2.4
Name: obskit
Version: 1.5.0
Summary: Production-ready observability toolkit for Python microservices with RED/Golden/USE metrics, tracing, logging, and resilience patterns
Project-URL: Homepage, https://github.com/talaatmagdyx/obskit
Project-URL: Documentation, https://github.com/talaatmagdyx/obskit#readme
Project-URL: Repository, https://github.com/talaatmagdyx/obskit.git
Project-URL: Issues, https://github.com/talaatmagdyx/obskit/issues
Project-URL: Changelog, https://github.com/talaatmagdyx/obskit/blob/main/CHANGELOG.md
Author-email: Talaat Magdy <talaatmagdy75@gmail.com>
Maintainer-email: Talaat Magdy <talaatmagdy75@gmail.com>
License-Expression: MIT
License-File: LICENSE
Keywords: RED-method,SLO,USE-method,circuit-breaker,distributed-tracing,golden-signals,health-check,logging,metrics,microservices,monitoring,observability,opentelemetry,prometheus,resilience,structured-logging,tracing
Classifier: Development Status :: 5 - Production/Stable
Classifier: Environment :: Web Environment
Classifier: Framework :: Django
Classifier: Framework :: FastAPI
Classifier: Framework :: Flask
Classifier: Intended Audience :: Developers
Classifier: Intended Audience :: System Administrators
Classifier: License :: OSI Approved :: MIT License
Classifier: Natural Language :: English
Classifier: Operating System :: OS Independent
Classifier: Programming Language :: Python :: 3
Classifier: Programming Language :: Python :: 3.11
Classifier: Programming Language :: Python :: 3.12
Classifier: Programming Language :: Python :: 3.13
Classifier: Topic :: Software Development :: Libraries :: Python Modules
Classifier: Topic :: System :: Distributed Computing
Classifier: Topic :: System :: Logging
Classifier: Topic :: System :: Monitoring
Classifier: Typing :: Typed
Requires-Python: >=3.11
Requires-Dist: pyyaml<7.0.0,>=6.0.0
Requires-Dist: structlog<26.0.0,>=23.1.0
Provides-Extra: alertmanager
Requires-Dist: httpx<1.0.0,>=0.25.0; extra == 'alertmanager'
Provides-Extra: all
Requires-Dist: fastapi<1.0.0,>=0.100.0; extra == 'all'
Requires-Dist: opentelemetry-api<2.0.0,>=1.20.0; extra == 'all'
Requires-Dist: opentelemetry-exporter-otlp<2.0.0,>=1.20.0; extra == 'all'
Requires-Dist: opentelemetry-sdk<2.0.0,>=1.20.0; extra == 'all'
Requires-Dist: prometheus-client<1.0.0,>=0.19.0; extra == 'all'
Requires-Dist: redis<8.0.0,>=5.0.0; extra == 'all'
Requires-Dist: starlette<1.0.0,>=0.27.0; extra == 'all'
Provides-Extra: dev
Requires-Dist: asciinema<3.0.0,>=2.4.0; extra == 'dev'
Requires-Dist: bandit[toml]<2.0.0,>=1.7.0; extra == 'dev'
Requires-Dist: mypy<2.0.0,>=1.8.0; extra == 'dev'
Requires-Dist: pip-audit<3.0.0,>=2.6.0; extra == 'dev'
Requires-Dist: pre-commit<5.0.0,>=3.6.0; extra == 'dev'
Requires-Dist: pytest-asyncio<2.0.0,>=0.23.0; extra == 'dev'
Requires-Dist: pytest-benchmark<6.0.0,>=4.0.0; extra == 'dev'
Requires-Dist: pytest-cov<8.0.0,>=4.1.0; extra == 'dev'
Requires-Dist: pytest-timeout<3.0.0,>=2.2.0; extra == 'dev'
Requires-Dist: pytest-xdist<4.0.0,>=3.5.0; extra == 'dev'
Requires-Dist: pytest<10.0.0,>=8.0.0; extra == 'dev'
Requires-Dist: ruff<1.0.0,>=0.3.0; extra == 'dev'
Requires-Dist: safety<4.0.0,>=2.3.0; extra == 'dev'
Requires-Dist: types-pyyaml>=6.0.0; extra == 'dev'
Requires-Dist: types-redis>=4.6.0; extra == 'dev'
Provides-Extra: django
Requires-Dist: django<6.0.0,>=4.0.0; extra == 'django'
Provides-Extra: docs
Requires-Dist: furo>=2024.1.0; extra == 'docs'
Requires-Dist: myst-parser>=3.0.0; extra == 'docs'
Requires-Dist: sphinx-autobuild>=2024.0.0; extra == 'docs'
Requires-Dist: sphinx-autodoc-typehints>=2.0.0; extra == 'docs'
Requires-Dist: sphinx-copybutton>=0.5.0; extra == 'docs'
Requires-Dist: sphinx>=7.2.0; extra == 'docs'
Requires-Dist: sphinxcontrib-mermaid>=0.9.0; extra == 'docs'
Provides-Extra: fastapi
Requires-Dist: fastapi<1.0.0,>=0.100.0; extra == 'fastapi'
Requires-Dist: starlette<1.0.0,>=0.27.0; extra == 'fastapi'
Provides-Extra: flask
Requires-Dist: flask<4.0.0,>=2.0.0; extra == 'flask'
Requires-Dist: werkzeug<4.0.0,>=2.0.0; extra == 'flask'
Provides-Extra: full
Requires-Dist: django<6.0.0,>=4.0.0; extra == 'full'
Requires-Dist: fastapi<1.0.0,>=0.100.0; extra == 'full'
Requires-Dist: flask<4.0.0,>=2.0.0; extra == 'full'
Requires-Dist: httpx<1.0.0,>=0.25.0; extra == 'full'
Requires-Dist: loguru<1.0.0,>=0.7.0; extra == 'full'
Requires-Dist: opentelemetry-api<2.0.0,>=1.20.0; extra == 'full'
Requires-Dist: opentelemetry-exporter-otlp-proto-grpc<2.0.0,>=1.20.0; extra == 'full'
Requires-Dist: opentelemetry-exporter-otlp<2.0.0,>=1.20.0; extra == 'full'
Requires-Dist: opentelemetry-sdk<2.0.0,>=1.20.0; extra == 'full'
Requires-Dist: prometheus-client<1.0.0,>=0.19.0; extra == 'full'
Requires-Dist: redis[hiredis]<8.0.0,>=5.0.0; extra == 'full'
Requires-Dist: starlette<1.0.0,>=0.27.0; extra == 'full'
Requires-Dist: werkzeug<4.0.0,>=2.0.0; extra == 'full'
Provides-Extra: loguru
Requires-Dist: loguru<1.0.0,>=0.7.0; extra == 'loguru'
Provides-Extra: metrics
Requires-Dist: prometheus-client<1.0.0,>=0.19.0; extra == 'metrics'
Provides-Extra: otlp-metrics
Requires-Dist: opentelemetry-api<2.0.0,>=1.20.0; extra == 'otlp-metrics'
Requires-Dist: opentelemetry-exporter-otlp-proto-grpc<2.0.0,>=1.20.0; extra == 'otlp-metrics'
Requires-Dist: opentelemetry-sdk<2.0.0,>=1.20.0; extra == 'otlp-metrics'
Provides-Extra: pushgateway
Requires-Dist: prometheus-client<1.0.0,>=0.19.0; extra == 'pushgateway'
Provides-Extra: pydantic
Requires-Dist: pydantic-settings<3.0.0,>=2.0.0; extra == 'pydantic'
Provides-Extra: redis
Requires-Dist: redis<8.0.0,>=5.0.0; extra == 'redis'
Provides-Extra: redis-async
Requires-Dist: redis[hiredis]<8.0.0,>=5.0.0; extra == 'redis-async'
Provides-Extra: security
Requires-Dist: pip-audit<3.0.0,>=2.6.0; extra == 'security'
Requires-Dist: safety<4.0.0,>=2.3.0; extra == 'security'
Provides-Extra: test-integration
Requires-Dist: httpx<1.0.0,>=0.25.0; extra == 'test-integration'
Requires-Dist: testcontainers[redis]<5.0.0,>=4.0.0; extra == 'test-integration'
Provides-Extra: tracing
Requires-Dist: opentelemetry-api<2.0.0,>=1.20.0; extra == 'tracing'
Requires-Dist: opentelemetry-exporter-otlp<2.0.0,>=1.20.0; extra == 'tracing'
Requires-Dist: opentelemetry-sdk<2.0.0,>=1.20.0; extra == 'tracing'
